{
  "type": "minecraft:entity",
  "pools": [
    {
      "rolls": 1,
      "bonus_rolls": 1,
      "entries": [
        {
          "type": "minecraft:item",
          "name": "minecraft:snowball",
          "functions": [
            {
              "function": "minecraft:set_count",
              "count": {
                "type": "minecraft:uniform",
                "min": 1,
                "max": 3
              }
            }
          ]
        },
        {
          "type": "minecraft:item",
          "name": "winterwonders:frost_essence",
          "conditions": [
            {
              "condition": "minecraft:random_chance_with_looting",
              "chance": 0.1,
              "looting_multiplier": 3
            }
          ]
        },
        {
          "type": "minecraft:item",
          "name": "winterwonders:frost_essence",
          "conditions": [
            {
              "condition": "minecraft:random_chance",
              "chance": 0.1
            }
          ]
        }
      ]
    }
  ]
}